{
    "posting_score": "준최6-Lv.2",
    "exposure_score": "44.73",
    "posting_score_details": [
        {
            "category": "키워드",
            "score": "85.97",
            "evaluation": "적합",
            "percentage": "85.97%"
        },
        {
            "category": "주제",
            "score": "73.28",
            "evaluation": "적합",
            "percentage": "73.28%"
        },
        {
            "category": "콘텐츠",
            "score": "68.28",
            "evaluation": "적합",
            "percentage": "68.28%"
        },
        {
            "category": "형태소",
            "score": "65.12",
            "evaluation": "적합",
            "percentage": "65.12%"
        },
        {
            "category": "가독성",
            "score": "77.95",
            "evaluation": "적합",
            "percentage": "77.95%"
        },
        {
            "category": "후기/정보",
            "score": "5.00",
            "evaluation": "후기성",
            "percentage": "5.00%"
        }
    ],
    "publish_time": "2025-02-03 18",
    "exposure_status": "발행된지 167일 (20시간) 경과되었습니다. 발행된 게시물은 현재시간 2025-07-21 14:54:50 정상 노출됩니다.",
    "text_analysis": {
        "title_with_space": "35",
        "title_without_space": "28",
        "content_with_space": "1,398",
        "content_without_space": "1,065"
    },
    "morpheme_counts": {
        "morpheme_count": "268",
        "syllable_count": "334",
        "word_count": "109",
        "abusing_word_count": "2"
    },
    "image_analysis": {
        "valid_images": "8",
        "invalid_images": "2",
        "material_images": "0",
        "uploaded_images": "10",
        "content_images": "10",
        "invalid_image_urls": [
            "https://mblogthumb-phinf.pstatic.net/MjAyNTAyMDNfOTYg/MDAxNzM4NTcwMTMzMDgz.sGvTyqRpF5Y7-ExVqJ-yQOAbjqfBQMQEo_41RkpSr1wg.tXtUUNmIzntRGWuMCa8Yyx-V3X85awpHq5HCcB87o9og.PNG/004.png?type=w400",
            "https://mblogthumb-phinf.pstatic.net/MjAyNTAyMDNfMjMz/MDAxNzM4NTcwMTMzMDg3._YwYNRJtWWT_iHZ7rVm_iEynnO3oKaCnkwrhqC7tBWQg.DXBAyIbOGwzWCD7F5gU09K3-sOGgYTdODmz4jyqy7Ggg.PNG/005.png?type=w400"
        ]
    },
    "post_title": "어금니 치아사이 충치, 깨짐 인레이와 레진, 크라운으로 당일완성",
    "post_content": "본 블로그의 모든 포스팅은 여치타 원장에 의해서 직접 작성됩니다. 사진 자료 및 포스팅 내용에 대한 무단 도용 및 복제는 불가합니다. 오늘은 어금니깨짐과 치아사이 충치로 크라운 치료를 당일 완성하신 사례를 알아보겠습니다. 어금니깨짐 50대 여성 환자분 이셨습니다. 어금니깨짐으로 시리고 통증이 생겨서 내원 하셨는데요. 엑스레이 사진에서 화살표로 표시한 부위는 치아사이 충치로 꽤 심한 상태 였습니다. (좌) 왼쪽 위, (우) 오른쪽 위 치아사이 충치와 어금니깨짐, 그리고 씹는 면 충치와 사랑치 충치 등 상태가 별로 좋지 못했는데요. 치아사이 충치 좌, 우 엑스레이 사진 환자분에게 상태를 설명드리고 먼저 왼쪽 부터 치료 하기로 했습니다. 치아사이 충치는 작은 어금니 2개로 인레이 치료를 하기로 했는데요. 큰 어금니 같은 경우 깨져버려서 크라운으로 치료 했습니다. 맨 끝 어금니의 씹는 면 충치는 크기가 비교적 작은 편 이라서 레진으로 치료가 되었는데요. 충치가 있었던 사랑니 부터 발치를 진행 해드렸습니다. 이후 인레이 2개와 크라운 1개, 레진 1개를 시작 했는데요. 아침에 시작하여 충치제거와 치아 다듬기 완료 후 스캔 했습니다. 오후에는 인레이, 크라운 제작이 완료 되어 부착 해드렸는데요. 기공실을 운영하고 있기 때문에 빠르게 환자분 개인의 맞춤으로 보철물 제작이 가능합니다. 그럼 치료 전 후 모습을 비교해보며 오늘 사례를 마치겠습니다. 환자분께서는 굉장히 만족하셨습니다. 무엇보다 하루만에 이렇게 레진, 인레이 크라운치료 까지 모두 마무리를 할 수 있다는 사실에 감탄 하셨는데요. 추후 오른쪽도 치료 받으시기 바라며 정기적으로 검진을 받으시길 바랍니다. *촬영일자* 전 2025.2 ,후 2025. 2 (3시간 경과 후) *모든 치료 전후 사진은 동일조건에서 촬영되었으며 본원에서 실제 진료한 사진으로 의료법 제23조, 제56조에 의거하여 환자분의 동의를 얻어 게재합니다. 개인의 차이에 따라 시술 및 수술 후 부작용이 발생할 수 있으며 의료진과 충분한 상담을 권해드립니다. 맺음말 오늘 이렇게 어금니깨짐으로 내원 해주신 환자분의 레진 인레이 크라운 당일 치료 사례를 함께 알아보았는데요. 치과 치료 같은 경우에 기본적으로 아프기 시작할 때 오시면 늦습니다. 그렇기 때문에 정기적인 검진을 받으시는것이 좋다고 항상 강조하여 이야기 드리곤 하는 편 인데요. 최소 6개월에서 12개월 사이에는 꼭 정기적으로 검진 받는게 좋습니다. 지금 당장 시간이 없다고, 비용이 부담 된다고 하시면서 미룰 순 있지만 그렇게 미루시게 되면 추후에는 더욱 큰 비용과 시간이 필요할지도 모릅니다. 2025년 에는 치아 건강 걱정 없도록 가까운 치과에서 검진 받으시기 바랍니다. 제가 준비한 내용은 여기까지입니다. 오늘도 찾아주셔서 감사합니다. 어금니 치아사이 충치, 깨짐 인레이와 레진, 크라운으로 당일완성",
    "abusing_words": {
        "adult_words": "",
        "harmful_words": "",
        "commercial_words": "비용(2), 상담(1)",
        "excessive_words": "충치(11), 치료(11)"
    },
    "category_analysis": [
        {
            "category_name": "건강·의학",
            "percentage": "56.38%",
            "keywords": "충치(10), 치료(10), 어금니(9), 인레이(6), 크라운(6), 환자분(6), 치아사이(6), 정기적(3), 상태(3), 당일(2), 엑스레이(2), 내원(2), 오른쪽(2), 왼쪽(2), 경우(2), 검진(2), 치과(2), 추후(2), 치아(1), 필요(1), 통증(1), 의료법(1), 기공실(1), 무엇(1), 크라운치료(1), 보철물(1), 기본적(1), 사이(1), 당장(1), 하루만(1), 이후(1), 본원(1), 부담(1), 부위(1), 발치(1), 발생(1), 모습(1), 무단(1), 부작용(1), 사랑니(1), 건강(1), 전후(1), 의료진(1), 여성(1), 수술(1), 시술(1), 진료(1)"
        },
        {
            "category_name": "비즈니스·경제",
            "percentage": "10.11%",
            "keywords": "때문(2), 포스팅(2), 내용(2), 개인(2), 최소(1), 강조(1), 오늘(1), 차이(1), 완성(1), 도용(1), 게재(1), 동의(1), 마무리(1), 아침(1), 진행(1)"
        },
        {
            "category_name": "IT·컴퓨터",
            "percentage": "5.85%",
            "keywords": "사진(5), 화살표(1), 스캔(1), 표시(1), 크기(1), 부착(1), 복제(1)"
        },
        {
            "category_name": "교육·학문",
            "percentage": "4.79%",
            "keywords": "시작(3), 운영(1), 준비(1), 비교적(1), 걱정(1), 맞춤(1), 가능(1)"
        },
        {
            "category_name": "사회·정치",
            "percentage": "3.19%",
            "keywords": "비용(2), 여기(1), 촬영(1), 자료(1), 사실(1)"
        },
        {
            "category_name": "취미",
            "percentage": "3.19%",
            "keywords": "레진(5), 만족(1)"
        },
        {
            "category_name": "상품리뷰",
            "percentage": "2.66%",
            "keywords": "제작(2), 완료(2), 비교(1)"
        },
        {
            "category_name": "맛집",
            "percentage": "2.13%",
            "keywords": "이야기(1), 여치(1), 불가(1), 감탄(1)"
        },
        {
            "category_name": "일상·생각",
            "percentage": "1.6%",
            "keywords": "감사(1), 블로그(1), 맺음말(1)"
        },
        {
            "category_name": "세계여행",
            "percentage": "1.6%",
            "keywords": "시간(2), 오후(1)"
        },
        {
            "category_name": "미분류",
            "percentage": "1.6%",
            "keywords": "사례(3)"
        },
        {
            "category_name": "음악",
            "percentage": "1.06%",
            "keywords": "상담(1), 작성(1)"
        },
        {
            "category_name": "패션·미용",
            "percentage": "1.06%",
            "keywords": "원장(1), 실제(1)"
        },
        {
            "category_name": "요리·레시피",
            "percentage": "0.53%",
            "keywords": "다듬기(1)"
        },
        {
            "category_name": "인테리어·DIY",
            "percentage": "0.53%",
            "keywords": "설명(1)"
        },
        {
            "category_name": "국내여행",
            "percentage": "0.53%",
            "keywords": "의거(1)"
        }
    ],
    "morpheme_analysis_details": [
        {
            "morpheme_type": "체언",
            "percentage": "36.15%",
            "words": "충치(11), 치료(11), 어금니(9), 사이(7), 크라운(7), 환자(6), 인레이(6), 사진(5), 레진(5), 치아(5), 후(5), 개(4), 사례(3), 상태(3), 분(3), 당일(3), 시작(3), 정기(3), 시간(3), 편(2), 조(2), 오른쪽(2), 개월(2), 치과(2), 검진(2), 면(2), 비교(2), 개인(2), 완료(2), 제작(2), 경우(2), 때문(2), 위(2), 비용(2), 완성(2), 촬영(2), 왼쪽(2), 수(2), 내용(2), 내원(2), 추후(2), 좌(2), 포스팅(2), 엑스레이(2), 시술(1), 차이(1), 게재(1), 수술(1), 일자(1), 동일(1), 의거(1), 진료(1), 의료법(1), 실제(1), 본원(1), 전후(1), 조건(1), 동의(1), 강조(1), 건강(1), 년(1), 필요(1), 순(1), 걱정(1), 제(1), 감사(1), 오늘(1), 여기(1), 준비(1), 부담(1), 당장(1), 맺음말(1), 상담(1), 의료진(1), 발생(1), 기본(1), 때(1), 게(1), 최소(1), 이야기(1), 것(1), 부작용(1), 기공실(1), 우(1), 부위(1), 표시(1), 화살표(1), 사랑(1), 등(1), 사랑니(1), 크기(1), 끝(1), 설명(1), 통증(1), 여성(1), 자료(1), 작성(1), 원장(1), 여치(1), 무단(1), 도용(1), 대(1), 불가(1), 복제(1), 발치(1), 진행(1), 만족(1), 모습(1), 전(1), 가능(1), 무엇(1), 하루(1), 사실(1), 마무리(1), 만(1), 보철물(1), 맞춤(1), 다듬기(1), 제거(1), 아침(1), 이후(1), 스캔(1), 오후(1), 운영(1), 블로그(1), 부착(1), 감탄(1)"
        },
        {
            "morpheme_type": "조사",
            "percentage": "15.54%",
            "words": "에(14), 를(10), 으로(10), 는(9), 이(8), 의(6), 로(6), 가(5), 을(5), 와(5), 에서(5), 과(4), 은(4), 도(3), 부터(2), 까지(2), 께서(1), 에게(1), 보다(1)"
        },
        {
            "morpheme_type": "용언",
            "percentage": "12.92%",
            "words": "깨(6), 받(5), 있(5), 치아(3), 했(3), 좋(3), 하(3), 되(2), 검(2), 같(2), 알아보(2), 드렸(2), 주(2), 바랍니다(2), 큰(2), 없(2), 씹(2), 이(2), 드리(2), 작(2), 찾(1), 늦(1), 오(1), 미루(1), 아프(1), 그렇(1), 인데요(1), 입니다(1), 모릅니다(1), 미룰(1), 가까운(1), 드립니다(1), 인(1), 빠르(1), 였(1), 못했(1), 깨져(1), 심한(1), 생겨서(1), 대한(1), 시리(1), 버려서(1), 의해서(1), 얻(1), 따라(1), 바라(1), 할(1), 보(1), 마치(1), 권해(1)"
        },
        {
            "morpheme_type": "어말 어미",
            "percentage": "10.92%",
            "words": "습니다(11), 는데요(8), 기(7), 짐(6), 는(5), 은(4), 여(3), 고(3), 으며(2), 진(2), 면(2), 다고(2), 며(2), 게(2), 어(2), 면서(1), 지만(1), 도록(1), 지(1), 아(1), 곤(1), 길(1), 던(1), 라서(1), 다는(1)"
        },
        {
            "morpheme_type": "불능",
            "percentage": "10.31%",
            "words": ".(32), ,(11), 2(4), )(3), 2025(3), ((3), *(3), 1(2), 6(1), 12(1), 56(1), 23(1), 3(1), 50(1)"
        },
        {
            "morpheme_type": "접미사",
            "percentage": "6.31%",
            "words": "하(9), 적(5), 합니다(4), 한(4), 해(4), 분(3), 할(2), 되(2), 했(2), 된다고(1), 할지(1), 경(1), 치(1), 타(1), 됩니다(1)"
        },
        {
            "morpheme_type": "부사",
            "percentage": "3.38%",
            "words": "및(3), 오늘(3), 이렇게(2), 항상(1), 함께(1), 꼭(1), 그렇게(1), 더욱(1), 모두(1), 지금(1), 굉장히(1), 그리고(1), 꽤(1), 별로(1), 먼저(1), 그럼(1), 직접(1)"
        },
        {
            "morpheme_type": "선어말 어미",
            "percentage": "3.08%",
            "words": "으시(4), 셨(4), 시(3), 었(3), 겠(2), 신(2), 셔서(1), 았(1)"
        },
        {
            "morpheme_type": "관형사",
            "percentage": "0.77%",
            "words": "모든(2), 전(1), 맨(1), 본(1)"
        },
        {
            "morpheme_type": "접두사",
            "percentage": "0.31%",
            "words": "제(2)"
        },
        {
            "morpheme_type": "감탄사",
            "percentage": "0.15%",
            "words": "우(1)"
        },
        {
            "morpheme_type": "어근",
            "percentage": "0.15%",
            "words": "충분(1)"
        }
    ],
    "word_analysis": {
        "total_words": "109",
        "words": [
            {
                "word": "충치",
                "count": "10"
            },
            {
                "word": "치료",
                "count": "10"
            },
            {
                "word": "어금니",
                "count": "9"
            },
            {
                "word": "인레이",
                "count": "6"
            },
            {
                "word": "환자분",
                "count": "6"
            },
            {
                "word": "치아사이",
                "count": "6"
            },
            {
                "word": "크라운",
                "count": "6"
            },
            {
                "word": "레진",
                "count": "5"
            },
            {
                "word": "사진",
                "count": "5"
            },
            {
                "word": "정기적",
                "count": "3"
            },
            {
                "word": "사례",
                "count": "3"
            },
            {
                "word": "시작",
                "count": "3"
            },
            {
                "word": "상태",
                "count": "3"
            },
            {
                "word": "때문",
                "count": "2"
            },
            {
                "word": "내용",
                "count": "2"
            },
            {
                "word": "치과",
                "count": "2"
            },
            {
                "word": "개인",
                "count": "2"
            },
            {
                "word": "검진",
                "count": "2"
            },
            {
                "word": "비용",
                "count": "2"
            },
            {
                "word": "시간",
                "count": "2"
            },
            {
                "word": "추후",
                "count": "2"
            },
            {
                "word": "제작",
                "count": "2"
            },
            {
                "word": "당일",
                "count": "2"
            },
            {
                "word": "완료",
                "count": "2"
            },
            {
                "word": "포스팅",
                "count": "2"
            },
            {
                "word": "내원",
                "count": "2"
            },
            {
                "word": "엑스레이",
                "count": "2"
            },
            {
                "word": "경우",
                "count": "2"
            },
            {
                "word": "오른쪽",
                "count": "2"
            },
            {
                "word": "왼쪽",
                "count": "2"
            },
            {
                "word": "가능",
                "count": "1"
            },
            {
                "word": "모습",
                "count": "1"
            },
            {
                "word": "만족",
                "count": "1"
            },
            {
                "word": "비교",
                "count": "1"
            },
            {
                "word": "마무리",
                "count": "1"
            },
            {
                "word": "사실",
                "count": "1"
            },
            {
                "word": "맞춤",
                "count": "1"
            },
            {
                "word": "하루만",
                "count": "1"
            },
            {
                "word": "무엇",
                "count": "1"
            },
            {
                "word": "충치제거",
                "count": "1"
            },
            {
                "word": "크기",
                "count": "1"
            },
            {
                "word": "설명",
                "count": "1"
            },
            {
                "word": "동일조건",
                "count": "1"
            },
            {
                "word": "비교적",
                "count": "1"
            },
            {
                "word": "발치",
                "count": "1"
            },
            {
                "word": "기공실",
                "count": "1"
            },
            {
                "word": "오후",
                "count": "1"
            },
            {
                "word": "아침",
                "count": "1"
            },
            {
                "word": "운영",
                "count": "1"
            },
            {
                "word": "필요",
                "count": "1"
            },
            {
                "word": "사이",
                "count": "1"
            },
            {
                "word": "강조",
                "count": "1"
            },
            {
                "word": "기본적",
                "count": "1"
            },
            {
                "word": "사랑치",
                "count": "1"
            },
            {
                "word": "준비",
                "count": "1"
            },
            {
                "word": "감사",
                "count": "1"
            },
            {
                "word": "오늘",
                "count": "1"
            },
            {
                "word": "여기",
                "count": "1"
            },
            {
                "word": "상담",
                "count": "1"
            },
            {
                "word": "의료진",
                "count": "1"
            },
            {
                "word": "의거",
                "count": "1"
            },
            {
                "word": "진료",
                "count": "1"
            },
            {
                "word": "본원",
                "count": "1"
            },
            {
                "word": "동의",
                "count": "1"
            },
            {
                "word": "게재",
                "count": "1"
            },
            {
                "word": "발생",
                "count": "1"
            },
            {
                "word": "부작용",
                "count": "1"
            },
            {
                "word": "차이",
                "count": "1"
            },
            {
                "word": "촬영",
                "count": "1"
            },
            {
                "word": "당장",
                "count": "1"
            },
            {
                "word": "크라운치료",
                "count": "1"
            },
            {
                "word": "보철물",
                "count": "1"
            },
            {
                "word": "부착",
                "count": "1"
            },
            {
                "word": "감탄",
                "count": "1"
            },
            {
                "word": "*촬영일자",
                "count": "1"
            },
            {
                "word": "실제",
                "count": "1"
            },
            {
                "word": "전후",
                "count": "1"
            },
            {
                "word": ",후",
                "count": "1"
            },
            {
                "word": "스캔",
                "count": "1"
            },
            {
                "word": "다듬기",
                "count": "1"
            },
            {
                "word": "도용",
                "count": "1"
            },
            {
                "word": "무단",
                "count": "1"
            },
            {
                "word": "자료",
                "count": "1"
            },
            {
                "word": "여성",
                "count": "1"
            },
            {
                "word": "사랑니",
                "count": "1"
            },
            {
                "word": "치아",
                "count": "1"
            },
            {
                "word": "이후",
                "count": "1"
            },
            {
                "word": "진행",
                "count": "1"
            },
            {
                "word": "의료법",
                "count": "1"
            },
            {
                "word": "시술",
                "count": "1"
            },
            {
                "word": "복제",
                "count": "1"
            },
            {
                "word": "작성",
                "count": "1"
            },
            {
                "word": "원장",
                "count": "1"
            },
            {
                "word": "불가",
                "count": "1"
            },
            {
                "word": "완성",
                "count": "1"
            },
            {
                "word": "표시",
                "count": "1"
            },
            {
                "word": "화살표",
                "count": "1"
            },
            {
                "word": "통증",
                "count": "1"
            },
            {
                "word": "여치",
                "count": "1"
            },
            {
                "word": "블로그",
                "count": "1"
            },
            {
                "word": "이야기",
                "count": "1"
            },
            {
                "word": "맺음말",
                "count": "1"
            },
            {
                "word": "수술",
                "count": "1"
            },
            {
                "word": "최소",
                "count": "1"
            },
            {
                "word": "부담",
                "count": "1"
            },
            {
                "word": "당일완성",
                "count": "1"
            },
            {
                "word": "걱정",
                "count": "1"
            },
            {
                "word": "건강",
                "count": "1"
            },
            {
                "word": "부위",
                "count": "1"
            }
        ]
    },
    "extracted_keywords": [
        {
            "rank": "1",
            "keyword": "치아사이충치",
            "search_volume_total": "600",
            "search_volume_pc": "60",
            "search_volume_mobile": "540",
            "clicks_pc": "-",
            "clicks_mobile": "-",
            "ctr_pc": "-",
            "ctr_mobile": "-",
            "competition": "높음",
            "ad_count": "3"
        },
        {
            "rank": "2",
            "keyword": "충치인레이",
            "search_volume_total": "420",
            "search_volume_pc": "60",
            "search_volume_mobile": "360",
            "clicks_pc": "-",
            "clicks_mobile": "-",
            "ctr_pc": "-",
            "ctr_mobile": "-",
            "competition": "높음",
            "ad_count": "3"
        },
        {
            "rank": "3",
            "keyword": "치아사이",
            "search_volume_total": "40",
            "search_volume_pc": "-",
            "search_volume_mobile": "40",
            "clicks_pc": "-",
            "clicks_mobile": "-",
            "ctr_pc": "-",
            "ctr_mobile": "-",
            "competition": "높음",
            "ad_count": "3"
        }
    ],
    "same_topic_posting": "치아사이 (159), 치아사이충치 (108), 충치인레이 (81)"
}